{ 
    "heading": { 
        "text": "Sell Points" 
    }, 

    "entryList": [ 
        { 
            "heading": {
                "text": "What is Our Deal?" 
            }, 
            "paragraphs": [ 
                { 
                    "text": "Nunc bibendum augue vitae enim sagittis, et lacinia lorem iaculis. Mauris at accumsan arcu, vel ultrices mauris. Aenean quis dictum massa. Mauris molestie risus massa, vitae placerat arcu pulvinar sed, consectetur adipiscing elit." 
                }
            ], 
            "image": { 
                "type": "featured", 
                "src": "/", 
                "alt": "Entry Image" 
            } 
        } 
    ]

}